{
    "description": "",
    "tags": [],
    "size": {
        "height": 1024,
        "width": 1000
    },
    "objects": [
        {
            "id": 1571351853,
            "classId": 13145456,
            "objectId": null,
            "description": "",
            "geometryType": "line",
            "labelerLogin": "demirarikan",
            "createdAt": "2024-06-27T21:58:41.471Z",
            "updatedAt": "2024-06-27T21:58:51.000Z",
            "tags": [],
            "classTitle": "rpe",
            "points": {
                "exterior": [
                    [
                        227,
                        386
                    ],
                    [
                        249,
                        383
                    ],
                    [
                        273,
                        382
                    ],
                    [
                        295,
                        379
                    ],
                    [
                        311,
                        376
                    ],
                    [
                        330,
                        375
                    ],
                    [
                        341,
                        373
                    ],
                    [
                        362,
                        367
                    ],
                    [
                        391,
                        362
                    ],
                    [
                        412,
                        356
                    ],
                    [
                        436,
                        350
                    ],
                    [
                        466,
                        347
                    ],
                    [
                        496,
                        342
                    ],
                    [
                        519,
                        335
                    ],
                    [
                        558,
                        325
                    ],
                    [
                        599,
                        310
                    ],
                    [
                        641,
                        296
                    ],
                    [
                        670,
                        284
                    ],
                    [
                        710,
                        266
                    ],
                    [
                        785,
                        243
                    ],
                    [
                        828,
                        228
                    ],
                    [
                        859,
                        216
                    ],
                    [
                        889,
                        203
                    ],
                    [
                        917,
                        191
                    ],
                    [
                        949,
                        178
                    ],
                    [
                        962,
                        171
                    ],
                    [
                        982,
                        163
                    ],
                    [
                        999,
                        157
                    ]
                ],
                "interior": []
            }
        },
        {
            "id": 1571351854,
            "classId": 13145455,
            "objectId": null,
            "description": "",
            "geometryType": "line",
            "labelerLogin": "demirarikan",
            "createdAt": "2024-06-27T21:58:55.633Z",
            "updatedAt": "2024-06-27T21:59:08.764Z",
            "tags": [],
            "classTitle": "ilm",
            "points": {
                "exterior": [
                    [
                        999,
                        8
                    ],
                    [
                        944,
                        29
                    ],
                    [
                        885,
                        51
                    ],
                    [
                        757,
                        97
                    ],
                    [
                        720,
                        108
                    ],
                    [
                        610,
                        144
                    ],
                    [
                        554,
                        165
                    ],
                    [
                        533,
                        170
                    ],
                    [
                        517,
                        176
                    ],
                    [
                        490,
                        178
                    ],
                    [
                        471,
                        181
                    ],
                    [
                        445,
                        192
                    ],
                    [
                        367,
                        211
                    ],
                    [
                        347,
                        213
                    ],
                    [
                        334,
                        217
                    ],
                    [
                        322,
                        222
                    ],
                    [
                        300,
                        223
                    ],
                    [
                        283,
                        223
                    ],
                    [
                        274,
                        227
                    ],
                    [
                        263,
                        228
                    ],
                    [
                        243,
                        228
                    ],
                    [
                        231,
                        226
                    ],
                    [
                        226,
                        225
                    ]
                ],
                "interior": []
            }
        },
        {
            "id": 1571351857,
            "classId": 13145454,
            "objectId": null,
            "description": "",
            "geometryType": "line",
            "labelerLogin": "demirarikan",
            "createdAt": "2024-06-27T21:59:16.245Z",
            "updatedAt": "2024-06-27T21:59:16.245Z",
            "tags": [],
            "classTitle": "tool",
            "points": {
                "exterior": [
                    [
                        220,
                        148
                    ],
                    [
                        150,
                        56
                    ],
                    [
                        107,
                        0
                    ]
                ],
                "interior": []
            }
        }
    ]
}