{
    "description": "",
    "tags": [],
    "size": {
        "height": 1024,
        "width": 1000
    },
    "objects": [
        {
            "id": 1560780786,
            "classId": 13145455,
            "objectId": null,
            "description": "",
            "geometryType": "line",
            "labelerLogin": "demirarikan",
            "createdAt": "2024-05-20T22:55:54.399Z",
            "updatedAt": "2024-05-20T22:56:07.149Z",
            "tags": [],
            "classTitle": "ilm",
            "points": {
                "exterior": [
                    [
                        23,
                        315
                    ],
                    [
                        71,
                        315
                    ],
                    [
                        115,
                        324
                    ],
                    [
                        149,
                        333
                    ],
                    [
                        197,
                        334
                    ],
                    [
                        227,
                        327
                    ],
                    [
                        255,
                        331
                    ],
                    [
                        291,
                        325
                    ],
                    [
                        318,
                        321
                    ],
                    [
                        367,
                        323
                    ],
                    [
                        406,
                        327
                    ],
                    [
                        448,
                        334
                    ],
                    [
                        478,
                        344
                    ],
                    [
                        501,
                        348
                    ],
                    [
                        527,
                        330
                    ],
                    [
                        559,
                        317
                    ],
                    [
                        590,
                        309
                    ],
                    [
                        620,
                        306
                    ],
                    [
                        641,
                        305
                    ],
                    [
                        668,
                        298
                    ],
                    [
                        698,
                        296
                    ],
                    [
                        717,
                        296
                    ],
                    [
                        779,
                        291
                    ],
                    [
                        831,
                        276
                    ],
                    [
                        881,
                        264
                    ],
                    [
                        918,
                        254
                    ],
                    [
                        950,
                        244
                    ],
                    [
                        979,
                        235
                    ],
                    [
                        999,
                        225
                    ]
                ],
                "interior": []
            }
        },
        {
            "id": 1560780788,
            "classId": 13145456,
            "objectId": null,
            "description": "",
            "geometryType": "line",
            "labelerLogin": "demirarikan",
            "createdAt": "2024-05-20T22:56:12.774Z",
            "updatedAt": "2024-05-20T22:56:19.121Z",
            "tags": [],
            "classTitle": "rpe",
            "points": {
                "exterior": [
                    [
                        29,
                        421
                    ],
                    [
                        98,
                        422
                    ],
                    [
                        180,
                        427
                    ],
                    [
                        249,
                        431
                    ],
                    [
                        322,
                        439
                    ],
                    [
                        394,
                        441
                    ],
                    [
                        458,
                        441
                    ],
                    [
                        533,
                        438
                    ],
                    [
                        620,
                        431
                    ],
                    [
                        690,
                        421
                    ],
                    [
                        794,
                        410
                    ],
                    [
                        866,
                        394
                    ],
                    [
                        933,
                        373
                    ],
                    [
                        999,
                        340
                    ]
                ],
                "interior": []
            }
        }
    ]
}