{
    "description": "",
    "tags": [],
    "size": {
        "height": 1024,
        "width": 1000
    },
    "objects": [
        {
            "id": 1577653724,
            "classId": 13145456,
            "objectId": null,
            "description": "",
            "geometryType": "line",
            "labelerLogin": "demirarikan",
            "createdAt": "2024-07-12T21:48:03.992Z",
            "updatedAt": "2024-07-12T21:48:10.249Z",
            "tags": [],
            "classTitle": "rpe",
            "points": {
                "exterior": [
                    [
                        227,
                        239
                    ],
                    [
                        260,
                        249
                    ],
                    [
                        288,
                        256
                    ],
                    [
                        312,
                        254
                    ],
                    [
                        322,
                        254
                    ],
                    [
                        352,
                        255
                    ],
                    [
                        388,
                        264
                    ],
                    [
                        406,
                        272
                    ],
                    [
                        439,
                        284
                    ],
                    [
                        459,
                        287
                    ],
                    [
                        471,
                        289
                    ],
                    [
                        495,
                        290
                    ],
                    [
                        515,
                        282
                    ],
                    [
                        543,
                        267
                    ],
                    [
                        569,
                        258
                    ],
                    [
                        618,
                        258
                    ],
                    [
                        643,
                        261
                    ],
                    [
                        692,
                        263
                    ],
                    [
                        733,
                        265
                    ],
                    [
                        768,
                        268
                    ],
                    [
                        808,
                        268
                    ],
                    [
                        852,
                        266
                    ],
                    [
                        888,
                        264
                    ],
                    [
                        917,
                        261
                    ],
                    [
                        951,
                        253
                    ],
                    [
                        982,
                        246
                    ],
                    [
                        999,
                        237
                    ]
                ],
                "interior": []
            }
        },
        {
            "id": 1577653726,
            "classId": 13145455,
            "objectId": null,
            "description": "",
            "geometryType": "line",
            "labelerLogin": "demirarikan",
            "createdAt": "2024-07-12T21:48:11.181Z",
            "updatedAt": "2024-07-12T21:48:20.376Z",
            "tags": [],
            "classTitle": "ilm",
            "points": {
                "exterior": [
                    [
                        230,
                        57
                    ],
                    [
                        256,
                        70
                    ],
                    [
                        277,
                        83
                    ],
                    [
                        299,
                        93
                    ],
                    [
                        316,
                        102
                    ],
                    [
                        337,
                        112
                    ],
                    [
                        353,
                        129
                    ],
                    [
                        365,
                        142
                    ],
                    [
                        379,
                        156
                    ],
                    [
                        392,
                        170
                    ],
                    [
                        405,
                        182
                    ],
                    [
                        415,
                        191
                    ],
                    [
                        427,
                        194
                    ],
                    [
                        441,
                        188
                    ],
                    [
                        456,
                        175
                    ],
                    [
                        471,
                        161
                    ],
                    [
                        485,
                        149
                    ],
                    [
                        496,
                        135
                    ],
                    [
                        514,
                        121
                    ],
                    [
                        562,
                        114
                    ],
                    [
                        575,
                        114
                    ],
                    [
                        592,
                        117
                    ],
                    [
                        611,
                        118
                    ],
                    [
                        619,
                        116
                    ],
                    [
                        627,
                        98
                    ],
                    [
                        639,
                        88
                    ],
                    [
                        653,
                        88
                    ],
                    [
                        660,
                        97
                    ],
                    [
                        670,
                        113
                    ],
                    [
                        687,
                        121
                    ],
                    [
                        706,
                        121
                    ],
                    [
                        727,
                        117
                    ],
                    [
                        753,
                        117
                    ],
                    [
                        779,
                        117
                    ],
                    [
                        795,
                        117
                    ],
                    [
                        818,
                        116
                    ],
                    [
                        833,
                        115
                    ],
                    [
                        865,
                        113
                    ],
                    [
                        888,
                        115
                    ],
                    [
                        907,
                        109
                    ],
                    [
                        917,
                        97
                    ],
                    [
                        932,
                        89
                    ],
                    [
                        962,
                        92
                    ],
                    [
                        982,
                        105
                    ],
                    [
                        999,
                        105
                    ],
                    [
                        999,
                        105
                    ]
                ],
                "interior": []
            }
        }
    ]
}