{
    "description": "",
    "tags": [],
    "size": {
        "height": 1024,
        "width": 1000
    },
    "objects": [
        {
            "id": 1564534522,
            "classId": 13145454,
            "objectId": null,
            "description": "",
            "geometryType": "line",
            "labelerLogin": "demirarikan",
            "createdAt": "2024-06-03T17:36:17.750Z",
            "updatedAt": "2024-06-03T17:36:17.750Z",
            "tags": [],
            "classTitle": "tool",
            "points": {
                "exterior": [
                    [
                        94,
                        0
                    ],
                    [
                        337,
                        324
                    ]
                ],
                "interior": []
            }
        },
        {
            "id": 1564534529,
            "classId": 13145455,
            "objectId": null,
            "description": "",
            "geometryType": "line",
            "labelerLogin": "demirarikan",
            "createdAt": "2024-06-03T17:36:27.581Z",
            "updatedAt": "2024-06-03T17:36:36.906Z",
            "tags": [],
            "classTitle": "ilm",
            "points": {
                "exterior": [
                    [
                        342,
                        370
                    ],
                    [
                        366,
                        361
                    ],
                    [
                        386,
                        350
                    ],
                    [
                        406,
                        341
                    ],
                    [
                        430,
                        332
                    ],
                    [
                        444,
                        325
                    ],
                    [
                        455,
                        323
                    ],
                    [
                        476,
                        324
                    ],
                    [
                        491,
                        324
                    ],
                    [
                        504,
                        322
                    ],
                    [
                        524,
                        318
                    ],
                    [
                        535,
                        316
                    ],
                    [
                        552,
                        315
                    ],
                    [
                        565,
                        316
                    ],
                    [
                        576,
                        316
                    ],
                    [
                        586,
                        312
                    ],
                    [
                        609,
                        310
                    ],
                    [
                        625,
                        308
                    ],
                    [
                        641,
                        307
                    ],
                    [
                        668,
                        306
                    ],
                    [
                        697,
                        294
                    ],
                    [
                        708,
                        292
                    ],
                    [
                        729,
                        294
                    ],
                    [
                        749,
                        294
                    ],
                    [
                        770,
                        288
                    ],
                    [
                        798,
                        282
                    ],
                    [
                        827,
                        275
                    ],
                    [
                        845,
                        269
                    ],
                    [
                        861,
                        264
                    ],
                    [
                        879,
                        261
                    ],
                    [
                        889,
                        257
                    ],
                    [
                        909,
                        253
                    ],
                    [
                        922,
                        249
                    ],
                    [
                        939,
                        243
                    ],
                    [
                        951,
                        241
                    ],
                    [
                        963,
                        238
                    ],
                    [
                        975,
                        233
                    ],
                    [
                        986,
                        229
                    ],
                    [
                        999,
                        225
                    ]
                ],
                "interior": []
            }
        },
        {
            "id": 1564534539,
            "classId": 13145456,
            "objectId": null,
            "description": "",
            "geometryType": "line",
            "labelerLogin": "demirarikan",
            "createdAt": "2024-06-03T17:36:43.008Z",
            "updatedAt": "2024-06-03T17:36:49.304Z",
            "tags": [],
            "classTitle": "rpe",
            "points": {
                "exterior": [
                    [
                        341,
                        443
                    ],
                    [
                        372,
                        450
                    ],
                    [
                        399,
                        451
                    ],
                    [
                        430,
                        451
                    ],
                    [
                        453,
                        448
                    ],
                    [
                        492,
                        444
                    ],
                    [
                        511,
                        439
                    ],
                    [
                        529,
                        438
                    ],
                    [
                        557,
                        436
                    ],
                    [
                        575,
                        434
                    ],
                    [
                        595,
                        433
                    ],
                    [
                        613,
                        433
                    ],
                    [
                        636,
                        433
                    ],
                    [
                        660,
                        431
                    ],
                    [
                        687,
                        428
                    ],
                    [
                        713,
                        423
                    ],
                    [
                        764,
                        415
                    ],
                    [
                        817,
                        403
                    ],
                    [
                        856,
                        393
                    ],
                    [
                        892,
                        385
                    ],
                    [
                        932,
                        372
                    ],
                    [
                        956,
                        365
                    ],
                    [
                        983,
                        358
                    ],
                    [
                        999,
                        347
                    ]
                ],
                "interior": []
            }
        }
    ]
}