{
    "description": "",
    "tags": [],
    "size": {
        "height": 1024,
        "width": 1000
    },
    "objects": [
        {
            "id": 1564518590,
            "classId": 13145454,
            "objectId": null,
            "description": "",
            "geometryType": "line",
            "labelerLogin": "demirarikan",
            "createdAt": "2024-06-03T17:12:04.311Z",
            "updatedAt": "2024-06-03T17:12:04.311Z",
            "tags": [],
            "classTitle": "tool",
            "points": {
                "exterior": [
                    [
                        96,
                        0
                    ],
                    [
                        278,
                        239
                    ]
                ],
                "interior": []
            }
        },
        {
            "id": 1564518594,
            "classId": 13145455,
            "objectId": null,
            "description": "",
            "geometryType": "line",
            "labelerLogin": "demirarikan",
            "createdAt": "2024-06-03T17:12:09.250Z",
            "updatedAt": "2024-06-03T17:12:21.475Z",
            "tags": [],
            "classTitle": "ilm",
            "points": {
                "exterior": [
                    [
                        281,
                        315
                    ],
                    [
                        294,
                        313
                    ],
                    [
                        301,
                        310
                    ],
                    [
                        312,
                        308
                    ],
                    [
                        327,
                        307
                    ],
                    [
                        341,
                        312
                    ],
                    [
                        364,
                        315
                    ],
                    [
                        380,
                        317
                    ],
                    [
                        399,
                        318
                    ],
                    [
                        425,
                        319
                    ],
                    [
                        444,
                        319
                    ],
                    [
                        464,
                        323
                    ],
                    [
                        486,
                        324
                    ],
                    [
                        503,
                        319
                    ],
                    [
                        523,
                        312
                    ],
                    [
                        559,
                        309
                    ],
                    [
                        579,
                        308
                    ],
                    [
                        602,
                        307
                    ],
                    [
                        627,
                        306
                    ],
                    [
                        648,
                        304
                    ],
                    [
                        689,
                        293
                    ],
                    [
                        701,
                        289
                    ],
                    [
                        722,
                        293
                    ],
                    [
                        739,
                        291
                    ],
                    [
                        759,
                        285
                    ],
                    [
                        780,
                        281
                    ],
                    [
                        803,
                        277
                    ],
                    [
                        821,
                        271
                    ],
                    [
                        840,
                        266
                    ],
                    [
                        859,
                        264
                    ],
                    [
                        874,
                        260
                    ],
                    [
                        895,
                        253
                    ],
                    [
                        906,
                        250
                    ],
                    [
                        937,
                        244
                    ],
                    [
                        953,
                        241
                    ],
                    [
                        972,
                        230
                    ],
                    [
                        989,
                        223
                    ],
                    [
                        999,
                        222
                    ]
                ],
                "interior": []
            }
        },
        {
            "id": 1564518602,
            "classId": 13145456,
            "objectId": null,
            "description": "",
            "geometryType": "line",
            "labelerLogin": "demirarikan",
            "createdAt": "2024-06-03T17:12:23.752Z",
            "updatedAt": "2024-06-03T17:12:33.167Z",
            "tags": [],
            "classTitle": "rpe",
            "points": {
                "exterior": [
                    [
                        280,
                        436
                    ],
                    [
                        319,
                        438
                    ],
                    [
                        349,
                        434
                    ],
                    [
                        382,
                        434
                    ],
                    [
                        424,
                        434
                    ],
                    [
                        455,
                        433
                    ],
                    [
                        486,
                        433
                    ],
                    [
                        521,
                        431
                    ],
                    [
                        556,
                        428
                    ],
                    [
                        577,
                        426
                    ],
                    [
                        603,
                        424
                    ],
                    [
                        628,
                        421
                    ],
                    [
                        657,
                        419
                    ],
                    [
                        684,
                        414
                    ],
                    [
                        706,
                        410
                    ],
                    [
                        750,
                        405
                    ],
                    [
                        770,
                        400
                    ],
                    [
                        804,
                        395
                    ],
                    [
                        831,
                        388
                    ],
                    [
                        865,
                        380
                    ],
                    [
                        906,
                        371
                    ],
                    [
                        934,
                        362
                    ],
                    [
                        961,
                        355
                    ],
                    [
                        977,
                        349
                    ],
                    [
                        996,
                        344
                    ],
                    [
                        999,
                        336
                    ]
                ],
                "interior": []
            }
        }
    ]
}