{
    "description": "",
    "tags": [],
    "size": {
        "height": 1024,
        "width": 1000
    },
    "objects": [
        {
            "id": 1564516154,
            "classId": 13145456,
            "objectId": null,
            "description": "",
            "geometryType": "line",
            "labelerLogin": "demirarikan",
            "createdAt": "2024-06-03T16:59:17.312Z",
            "updatedAt": "2024-06-03T16:59:24.751Z",
            "tags": [],
            "classTitle": "rpe",
            "points": {
                "exterior": [
                    [
                        999,
                        352
                    ],
                    [
                        978,
                        363
                    ],
                    [
                        927,
                        378
                    ],
                    [
                        890,
                        394
                    ],
                    [
                        844,
                        403
                    ],
                    [
                        797,
                        417
                    ],
                    [
                        759,
                        425
                    ],
                    [
                        727,
                        429
                    ],
                    [
                        692,
                        435
                    ],
                    [
                        664,
                        438
                    ],
                    [
                        593,
                        448
                    ],
                    [
                        553,
                        454
                    ],
                    [
                        497,
                        465
                    ],
                    [
                        473,
                        473
                    ],
                    [
                        447,
                        481
                    ],
                    [
                        432,
                        490
                    ]
                ],
                "interior": []
            }
        },
        {
            "id": 1564516164,
            "classId": 13145454,
            "objectId": null,
            "description": "",
            "geometryType": "line",
            "labelerLogin": "demirarikan",
            "createdAt": "2024-06-03T16:59:30.421Z",
            "updatedAt": "2024-06-03T16:59:30.421Z",
            "tags": [],
            "classTitle": "tool",
            "points": {
                "exterior": [
                    [
                        423,
                        442
                    ],
                    [
                        95,
                        10
                    ]
                ],
                "interior": []
            }
        },
        {
            "id": 1564516167,
            "classId": 13145455,
            "objectId": null,
            "description": "",
            "geometryType": "line",
            "labelerLogin": "demirarikan",
            "createdAt": "2024-06-03T16:59:35.157Z",
            "updatedAt": "2024-06-03T16:59:47.798Z",
            "tags": [],
            "classTitle": "ilm",
            "points": {
                "exterior": [
                    [
                        419,
                        428
                    ],
                    [
                        440,
                        388
                    ],
                    [
                        458,
                        355
                    ],
                    [
                        479,
                        336
                    ],
                    [
                        496,
                        329
                    ],
                    [
                        517,
                        328
                    ],
                    [
                        536,
                        327
                    ],
                    [
                        554,
                        323
                    ],
                    [
                        575,
                        319
                    ],
                    [
                        593,
                        321
                    ],
                    [
                        619,
                        314
                    ],
                    [
                        653,
                        308
                    ],
                    [
                        669,
                        310
                    ],
                    [
                        683,
                        308
                    ],
                    [
                        698,
                        303
                    ],
                    [
                        715,
                        300
                    ],
                    [
                        729,
                        295
                    ],
                    [
                        751,
                        295
                    ],
                    [
                        765,
                        296
                    ],
                    [
                        772,
                        290
                    ],
                    [
                        786,
                        288
                    ],
                    [
                        806,
                        286
                    ],
                    [
                        820,
                        279
                    ],
                    [
                        844,
                        273
                    ],
                    [
                        862,
                        268
                    ],
                    [
                        883,
                        265
                    ],
                    [
                        919,
                        255
                    ],
                    [
                        942,
                        248
                    ],
                    [
                        963,
                        241
                    ],
                    [
                        981,
                        234
                    ],
                    [
                        995,
                        228
                    ],
                    [
                        999,
                        231
                    ]
                ],
                "interior": []
            }
        }
    ]
}